hdl/adder_1.sv
`default_nettype none
`timescale 1ns/1ps

// A 1 bit full adder that we can daisy chain to make a larger ripple carry adder.

module adder_1(a, b, c_in, sum, c_out);

input wire a, b, c_in;
output logic sum, c_out;

// Figure 5.3 from the text:
always_comb begin : adder_gates
  c_out = a&b | a&c_in | b&c_in;
  sum = c_in ^ a ^ b;
end
endmodule

hdl/icarcus_tests/test_adder_1.sv
module test_adder_1;

logic a, b, c_in;
logic sum, c_out;

logic exp_sum;
logic exp_cout;

adder_1 UUT (
  .a(a),
  .b(b),
  .c_in(c_in),
  .sum(sum),
  .c_out(c_out)
);

int errors = 0;

initial begin
  $dumpfile("wave.vcd");
  $dumpvars(0, test_adder_1);

  for (int i = 0; i < 8; i = i + 1) begin
    c_in = i[2];
    b    = i[1];
    a    = i[0];

    #1;

    exp_sum  = a ^ b ^ c_in;
    exp_cout = (a & b) | (a & c_in) | (b & c_in);

    if ({c_out, sum} !== {exp_cout, exp_sum}) begin
      $display("FAIL: %b%b%b expected %b%b got %b%b",
        a, b, c_in,
        exp_cout, exp_sum,
        c_out, sum
      );
      errors = errors + 1;
    end
  end

  if (errors == 0)
    $display("PASS");
  else
    $display("FAIL %0d errors", errors);

  $finish;
end

endmodule

dump.vcd
$date
	Sat May 23 14:37:07 2026
$end
$version
	Icarus Verilog
$end
$timescale
	1ps
$end
$scope module test_adder_1 $end
$scope module UUT $end
$var wire 1 ! a $end
$var wire 1 " b $end
$var wire 1 # c_in $end
$var reg 1 $ c_out $end
$var reg 1 % sum $end
$scope begin adder_gates $end
$upscope $end
$upscope $end
$upscope $end
$enddefinitions $end
$comment Show the parameter values. $end
$dumpall
$end
#0
$dumpvars
0%
0$
0#
0"
0!
$end
#1000
1%
1!
#2000
0!
1"
#3000
0%
1$
1!
#4000
1%
0$
0!
0"
1#
#5000
0%
1$
1!
#6000
0!
1"
#7000
1%
1!
